admob_ssv/__init__.py
admob_ssv/conf.py
admob_ssv/py.typed
admob_ssv/signals.py
admob_ssv/views.py
django_admob_ssv-3.4.0.dist-info/METADATA
django_admob_ssv-3.4.0.dist-info/WHEEL
django_admob_ssv-3.4.0.dist-info/licenses/LICENSE
django_admob_ssv-3.4.0.dist-info/RECORD
