Metadata-Version: 2.4
Name: django-admob-ssv
Version: 3.4.0
Summary: Admob server-side verification for Django projects
Project-URL: homepage, https://github.com/DoctorJohn/django-admob-ssv
Project-URL: repository, https://github.com/DoctorJohn/django-admob-ssv
Project-URL: documentation, https://github.com/DoctorJohn/django-admob-ssv
Author-email: Jonathan Ehwald <github@ehwald.info>
License: MIT
License-File: LICENSE
Classifier: Development Status :: 5 - Production/Stable
Classifier: Environment :: Web Environment
Classifier: Framework :: Django
Classifier: Framework :: Django :: 4.2
Classifier: Framework :: Django :: 5.0
Classifier: Framework :: Django :: 5.1
Classifier: Framework :: Django :: 5.2
Classifier: Intended Audience :: Developers
Classifier: License :: OSI Approved :: MIT License
Classifier: Operating System :: OS Independent
Classifier: Programming Language :: Python
Classifier: Programming Language :: Python :: 3
Classifier: Programming Language :: Python :: 3 :: Only
Classifier: Programming Language :: Python :: 3.10
Classifier: Programming Language :: Python :: 3.11
Classifier: Programming Language :: Python :: 3.12
Classifier: Programming Language :: Python :: 3.13
Classifier: Programming Language :: Python :: 3.14
Classifier: Topic :: Internet :: WWW/HTTP
Classifier: Topic :: Internet :: WWW/HTTP :: Dynamic Content
Classifier: Topic :: Software Development :: Libraries
Classifier: Topic :: Software Development :: Libraries :: Python Modules
Requires-Python: <4.0,>=3.10
Requires-Dist: django>=4.2
Requires-Dist: ecdsa<1.0.0,>=0.19.0
Requires-Dist: requests<3.0.0,>=2.30.0
